DNLAP/__init__.py
DNLAP/basic_ops.py
DNLAP/decompositions.py
DNLAP/direct_solvers.py
DNLAP/eigen.py
DNLAP/iterative_solvers.py
dnlap-0.0.7.dist-info/licenses/LICENSE
dnlap-0.0.7.dist-info/METADATA
dnlap-0.0.7.dist-info/WHEEL
dnlap-0.0.7.dist-info/top_level.txt
dnlap-0.0.7.dist-info/RECORD
